README.md
setup.py
Authlog.egg-info/PKG-INFO
Authlog.egg-info/SOURCES.txt
Authlog.egg-info/dependency_links.txt
Authlog.egg-info/not-zip-safe
Authlog.egg-info/top_level.txt
authlog/__init__.py
authlog/admin.py
authlog/apps.py
authlog/decorators.py
authlog/logadminmiddleware.py
authlog/models.py
authlog/management/__init__.py
authlog/management/commands/__init__.py
authlog/management/commands/authlog_dumplogin.py
authlog/management/commands/authlog_dumpview.py
authlog/migrations/0001_initial.py
authlog/migrations/0002_auto_20161229_1427.py
authlog/migrations/__init__.py