Metadata-Version: 1.1
Name: Authlog
Version: 0.11.3
Summary: Log Django Authentications and Admin page visits.
Home-page: http://www.imagescape.com
Author: Joe Jasinski
Author-email: jjasinski@imagescape.com
License: UNKNOWN
Platform: UNKNOWN
Classifier: Programming Language :: Python :: 3
